ncjishaku/__init__.py
ncjishaku/__main__.py
ncjishaku/codeblocks.py
ncjishaku/cog.py
ncjishaku/exception_handling.py
ncjishaku/flags.py
ncjishaku/formatting.py
ncjishaku/functools.py
ncjishaku/help_command.py
ncjishaku/hljs.py
ncjishaku/math.py
ncjishaku/meta.py
ncjishaku/models.py
ncjishaku/modules.py
ncjishaku/paginators.py
ncjishaku/py.typed
ncjishaku/shell.py
ncjishaku/types.py
ncjishaku/features/__init__.py
ncjishaku/features/baseclass.py
ncjishaku/features/filesystem.py
ncjishaku/features/guild.py
ncjishaku/features/invocation.py
ncjishaku/features/management.py
ncjishaku/features/python.py
ncjishaku/features/root_command.py
ncjishaku/features/shell.py
ncjishaku/features/sql.py
ncjishaku/features/voice.py
ncjishaku/features/scaffolds/cargo/Cargo.toml
ncjishaku/features/scaffolds/cargo/src/main.rs
ncjishaku/features/scaffolds/npm/index.js
ncjishaku/features/scaffolds/npm/package.json
ncjishaku/features/scaffolds/pyright/main.py
ncjishaku/features/scaffolds/pyright/pyrightconfig.json
ncjishaku/repl/__init__.py
ncjishaku/repl/compilation.py
ncjishaku/repl/disassembly.py
ncjishaku/repl/inspections.py
ncjishaku/repl/repl_builtins.py
ncjishaku/repl/scope.py
ncjishaku/repl/walkers.py
ncjishaku-3.0.0rc1.dist-info/licenses/LICENSE
ncjishaku-3.0.0rc1.dist-info/METADATA
ncjishaku-3.0.0rc1.dist-info/WHEEL
ncjishaku-3.0.0rc1.dist-info/entry_points.txt
ncjishaku-3.0.0rc1.dist-info/top_level.txt
ncjishaku-3.0.0rc1.dist-info/RECORD
