Metadata-Version: 2.4
Name: ncjishaku
Version: 3.0.0rc1
Summary: A nextcord extension including useful tools for bot development and debugging.
Author: CrystalAlpha358, Devon (scarletcafe) R
Maintainer: CrystalAlpha358
License-Expression: MIT
Project-URL: Homepage, https://github.com/CrystalAlpha358/ncjishaku
Project-URL: Documentation, https://ncjishaku.readthedocs.io/
Project-URL: Repository, https://github.com/CrystalAlpha358/ncjishaku
Project-URL: Issues, https://github.com/CrystalAlpha358/ncjishaku/issues
Keywords: jishaku,nextcord,discord,cog,repl,extension
Classifier: Development Status :: 4 - Beta
Classifier: Framework :: AsyncIO
Classifier: Intended Audience :: Developers
Classifier: Natural Language :: English
Classifier: Operating System :: OS Independent
Classifier: Programming Language :: Python :: 3 :: Only
Classifier: Programming Language :: Python :: 3.12
Classifier: Programming Language :: Python :: 3.13
Classifier: Programming Language :: Python :: 3.14
Classifier: Topic :: Communications :: Chat
Classifier: Topic :: Internet
Classifier: Topic :: Software Development :: Debuggers
Classifier: Topic :: Software Development :: Testing
Classifier: Topic :: Utilities
Requires-Python: >=3.12.0
License-File: LICENSE
Requires-Dist: braceexpand>=0.1.7
Requires-Dist: click>=8.1.7
Requires-Dist: nextcord>=3.0.0
Requires-Dist: import_expression<3.0.0,>=2.0.0
Requires-Dist: tabulate>=0.9.0
Requires-Dist: typing-extensions<5,>=4.3
Provides-Extra: docs
Requires-Dist: Sphinx<9,>=4.4.0; extra == "docs"
Requires-Dist: sphinxcontrib_trio>=1.1.2; extra == "docs"
Provides-Extra: procinfo
Requires-Dist: psutil>=5.9.5; extra == "procinfo"
Provides-Extra: profiling
Requires-Dist: line-profiler>=4.1.1; extra == "profiling"
Provides-Extra: publish
Requires-Dist: Jinja2>=3.1.2; extra == "publish"
Provides-Extra: test
Requires-Dist: coverage>=7.5.4; extra == "test"
Requires-Dist: ruff>=0.12.11; extra == "test"
Requires-Dist: pytest>=8.3.5; extra == "test"
Requires-Dist: pytest-asyncio>=0.24.0; extra == "test"
Requires-Dist: pytest-cov>=5.0.0; extra == "test"
Requires-Dist: pytest-mock>=3.14.1; extra == "test"
Provides-Extra: voice
Requires-Dist: nextcord[voice]>=3.0.0; extra == "voice"
Dynamic: license-file
